{
    "format_version": "1.20.30",
    "minecraft:recipe_shaped": {
        "description": {
            "identifier": "terra:tome_coagulate"
        },
        "tags": [
            "arcane_table"
        ],
        "pattern": [
            "SS#",
            "SLM",
            "#MR"
        ],
        "key": {
            "#": {
                "item": "terra:reverion"
            },
            "M": {
                "item": "terra:purified_malachite"
            },
            "R": {
                "item": "terra:rune_coagulate"
            },
            "S": {
                "item": "terra:scroll_coagulate"
            },
            "L": {
                "item": "minecraft:leather"
            }
        },
        "unlock": [
            {
                "item": "terra:rune_coagulate"
            }
        ],
        "result": {
            "item": "terra:tome_coagulate",
            "count": 1
        }
    }
}